src/__init__.py
src/agent_config.py
src/logging_config.py
src/main.py
src/server_settings.py
src/models/__init__.py
src/models/models.py
src/services/__init__.py
src/services/gitlab_service.py
src/tools/__init__.py
src/tools/setup_standards.py
src/utils/__init__.py
src/utils/os_utils.py
agent_coding_standards_mcp-1.0.1.dist-info/METADATA
agent_coding_standards_mcp-1.0.1.dist-info/WHEEL
agent_coding_standards_mcp-1.0.1.dist-info/entry_points.txt
agent_coding_standards_mcp-1.0.1.dist-info/RECORD
