Metadata-Version: 2.4
Name: agent-coding-standards-mcp
Version: 1.0.1
Summary: MCP Server for AI coding agent standards
Author-email: Teqnological <baonguyen@teqnological.asia>
Requires-Python: <3.14,>=3.13
Requires-Dist: aiofiles>=23.0
Requires-Dist: httpx[http2]>=0.26.0
Requires-Dist: mcp==1.25.0
Requires-Dist: pydantic-settings>=2.0.0
Requires-Dist: pydantic>=2.0
Requires-Dist: python-dotenv>=1.0.0
Requires-Dist: python-frontmatter>=1.0
